pywr/__init__.py
pywr/_component.cp310-win_amd64.pyd
pywr/_component.pxd
pywr/_core.cp310-win_amd64.pyd
pywr/_core.pxd
pywr/_model.cp310-win_amd64.pyd
pywr/core.py
pywr/dataframe_tools.py
pywr/h5tools.py
pywr/hashes.py
pywr/model.py
pywr/nodes.py
pywr/parameter_property.py
pywr/profiler.py
pywr/timestepper.py
pywr/domains/__init__.py
pywr/domains/groundwater.py
pywr/domains/river.py
pywr/notebook/__init__.py
pywr/notebook/draw_graph.js
pywr/notebook/figures.py
pywr/notebook/graph.css
pywr/notebook/sankey.py
pywr/notebook/save_graph.js
pywr/notebook/template.html
pywr/optimisation/__init__.py
pywr/optimisation/platypus.py
pywr/optimisation/pygmo.py
pywr/parameters/__init__.py
pywr/parameters/_activation_functions.cp310-win_amd64.pyd
pywr/parameters/_activation_functions.pxd
pywr/parameters/_control_curves.cp310-win_amd64.pyd
pywr/parameters/_control_curves.pxd
pywr/parameters/_hydropower.cp310-win_amd64.pyd
pywr/parameters/_hydropower.pxd
pywr/parameters/_parameters.cp310-win_amd64.pyd
pywr/parameters/_parameters.pxd
pywr/parameters/_polynomial.cp310-win_amd64.pyd
pywr/parameters/_polynomial.pxd
pywr/parameters/_thresholds.cp310-win_amd64.pyd
pywr/parameters/_thresholds.pxd
pywr/parameters/control_curves.py
pywr/parameters/groundwater.py
pywr/parameters/licenses.py
pywr/parameters/multi_model_parameters.py
pywr/parameters/parameters.py
pywr/recorders/__init__.py
pywr/recorders/_hydropower.cp310-win_amd64.pyd
pywr/recorders/_hydropower.pxd
pywr/recorders/_recorders.cp310-win_amd64.pyd
pywr/recorders/_recorders.pxd
pywr/recorders/_thresholds.cp310-win_amd64.pyd
pywr/recorders/_thresholds.pxd
pywr/recorders/calibration.py
pywr/recorders/events.py
pywr/recorders/kde.py
pywr/recorders/progress.py
pywr/recorders/recorders.py
pywr/solvers/__init__.py
pywr/solvers/cython_glpk.cp310-win_amd64.pyd
pywr/solvers/libglpk.pxd
pywr/utils/__init__.py
pywr/utils/bisect.py
pywr_stoch-1.21.0.post1.dist-info/LICENSE.txt
pywr_stoch-1.21.0.post1.dist-info/METADATA
pywr_stoch-1.21.0.post1.dist-info/WHEEL
pywr_stoch-1.21.0.post1.dist-info/top_level.txt
pywr_stoch-1.21.0.post1.dist-info/RECORD
