Metadata-Version: 2.1
Name: pywr-stoch
Version: 1.21.0.post1
Summary: Python Water Resource model
Home-page: https://github.com/pywr/pywr
Author: Joshua Arnott
Author-email: josh@snorfalorpagus.net
License-File: LICENSE.txt
Requires-Dist: pandas
Requires-Dist: networkx
Requires-Dist: scipy
Requires-Dist: tables
Requires-Dist: openpyxl
Requires-Dist: packaging
Provides-Extra: dev
Requires-Dist: sphinx ; extra == 'dev'
Requires-Dist: sphinx-rtd-theme ; extra == 'dev'
Requires-Dist: numpydoc ; extra == 'dev'
Requires-Dist: matplotlib ; extra == 'dev'
Requires-Dist: pytest ; extra == 'dev'
Requires-Dist: ipython ; extra == 'dev'
Requires-Dist: jinja2 ; extra == 'dev'
Requires-Dist: platypus-opt ; extra == 'dev'
Requires-Dist: pygmo ; extra == 'dev'
Provides-Extra: docs
Requires-Dist: sphinx ; extra == 'docs'
Requires-Dist: sphinx-rtd-theme ; extra == 'docs'
Requires-Dist: numpydoc ; extra == 'docs'
Requires-Dist: matplotlib ; extra == 'docs'
Provides-Extra: notebook
Requires-Dist: ipython ; extra == 'notebook'
Requires-Dist: jinja2 ; extra == 'notebook'
Requires-Dist: matplotlib ; extra == 'notebook'
Provides-Extra: optimisation
Requires-Dist: platypus-opt ; extra == 'optimisation'
Requires-Dist: pygmo ; extra == 'optimisation'
Provides-Extra: test
Requires-Dist: pytest ; extra == 'test'
Requires-Dist: ipython ; extra == 'test'
Requires-Dist: jinja2 ; extra == 'test'
Requires-Dist: matplotlib ; extra == 'test'
Requires-Dist: platypus-opt ; extra == 'test'
Requires-Dist: pygmo ; extra == 'test'
